{
    "mapping_fields": {
        "title": "title",
        "description": "notes",
        "keyword": "tags",
        "modified": "extras__modified",
        "publisher": "extras__publisher",
        "contactPoint": "maintainer",
        "mbox": "maintainer_email",
        "identifier": "extras__identifier",
        "accessLevel": "extras__accessLevel",
        "bureauCode": "extras__bureauCode",
        "programCode": "extras__programCode",
        "accessLevelComment": "extras__accessLevelComment",
        "license": "extras__license",
        "spatial": "extras__spatial",
        "temporal": "extras__temporal",
        "theme": "extras__theme",
        "dataDictionary": "extras__dataDictionary",
        "dataQuality": "extras__dataQuality",
        "accrualPeriodicity":"extras__accrualPeriodicity",
        "landingPage": "extras__landingPage",
        "language": "extras__language",
        "primaryITInvestmentUII": "extras__primaryITInvestmentUII",
        "references": "extras__references",
        "issued": "extras__issued",
        "systemOfRecords": "extras__systemOfRecords",
        "accessURL": null,
        "webService": null,
        "format": null,
        "distribution": null
    },
    "skip": ["accessURL", "webService", "format", "distribution", "processed_how"]
}